maison/__init__.py
maison/__main__.py
maison/config.py
maison/config_parser.py
maison/config_validator.py
maison/disk_filesystem.py
maison/errors.py
maison/protocols.py
maison/py.typed
maison/service.py
maison/typedefs.py
maison/utils.py
maison/parsers/__init__.py
maison/parsers/ini.py
maison/parsers/pyproject.py
maison/parsers/toml.py
maison-2.0.1.dist-info/licenses/LICENSE
maison-2.0.1.dist-info/METADATA
maison-2.0.1.dist-info/WHEEL
maison-2.0.1.dist-info/top_level.txt
maison-2.0.1.dist-info/RECORD
