Metadata-Version: 2.4
Name: maison
Version: 2.0.1
Summary: Read settings from config files
Author-email: Dom Batten <dominic.batten@googlemail.com>
License-Expression: MIT
Project-URL: Homepage, https://github.com/dbatten/maison
Project-URL: Repository, https://github.com/dbatten/maison
Keywords: maison
Classifier: Programming Language :: Python :: 3.9
Classifier: Programming Language :: Python :: 3 :: Only
Requires-Python: <4.0,>=3.9
License-File: LICENSE
Requires-Dist: loguru>=0.7.3
Requires-Dist: platformdirs>=4.3.8
Requires-Dist: tomli>=2.2.1; python_full_version < "3.11"
Requires-Dist: typer>=0.15.4
Requires-Dist: typing-extensions>=4.13.2
Dynamic: license-file
